deflatebr/__init__.py
deflatebr/deflate.py
deflatebr/utils.py
deflateBR-0.2.1.dist-info/LICENSE
deflateBR-0.2.1.dist-info/METADATA
deflateBR-0.2.1.dist-info/WHEEL
deflateBR-0.2.1.dist-info/top_level.txt
deflateBR-0.2.1.dist-info/RECORD
