Metadata-Version: 2.1
Name: deflateBR
Version: 0.2.1
Summary: Deflate Nominal Brazilian Reais
Home-page: http://github.com/neylsoncrepalde/deflatebr
Author: Neylson Crepalde & Fernando Meireles
Author-email: neylsoncrepalde@gmail.com
License: MIT
Keywords: deflate deflation economics salary wage finance
Platform: UNKNOWN
Classifier: Development Status :: 4 - Beta
Classifier: License :: OSI Approved :: MIT License
Classifier: Programming Language :: Python :: 3.6
Classifier: Programming Language :: Python :: 3.7
Classifier: Topic :: Office/Business :: Financial
Classifier: Topic :: Scientific/Engineering :: Mathematics
Requires-Python: >=3.6
Requires-Dist: requests
Requires-Dist: pandas
Requires-Dist: numpy
Requires-Dist: datetime
Requires-Dist: tqdm
